doc2poma/__init__.py
doc2poma/converter.py
doc2poma/version.py
doc2poma-0.1.5.dist-info/licenses/LICENSE
doc2poma-0.1.5.dist-info/METADATA
doc2poma-0.1.5.dist-info/WHEEL
doc2poma-0.1.5.dist-info/top_level.txt
doc2poma-0.1.5.dist-info/RECORD
