Metadata-Version: 2.4
Name: doc2poma
Version: 0.1.5
Summary: Convert PDFs, HTML, and images into structured .poma format
Author-email: "TIGON S.L.U." <info@poma.science>
License-Expression: MPL-2.0
Requires-Python: >=3.10
License-File: LICENSE
Requires-Dist: poma-senter
Requires-Dist: litellm
Requires-Dist: tiktoken
Requires-Dist: pandas
Requires-Dist: Pillow
Requires-Dist: pillow-heif
Requires-Dist: html2text
Requires-Dist: beautifulsoup4
Requires-Dist: pymupdf
Requires-Dist: pytest
Requires-Dist: cairosvg
Requires-Dist: pycairo
Requires-Dist: rlPyCairo
Requires-Dist: svglib
Requires-Dist: reportlab
Requires-Dist: wand
Requires-Dist: tenacity
Dynamic: license-file
